ieee_patch/__init__.py
ieee_patch/patch.py
ieee_patch/test_patch.py
ieee_patch/xml_pretty_print.py
dcs_ms_word_ieee_patch-0.2.2.dist-info/entry_points.txt
dcs_ms_word_ieee_patch-0.2.2.dist-info/WHEEL
dcs_ms_word_ieee_patch-0.2.2.dist-info/METADATA
dcs_ms_word_ieee_patch-0.2.2.dist-info/RECORD
