Metadata-Version: 2.1
Name: dcs-ms-word-ieee-patch
Version: 0.2.2
Summary: Patch IEEE citation format in Microsoft Word docx documents
Home-page: https://github.com/dotcs/ms-word-ieee-patch
Keywords: cli,cli-app,ms-word,ieee
Author: dotcs
Author-email: git@dotcs.me
Requires-Python: >=3.8,<4.0
Classifier: Development Status :: 4 - Beta
Classifier: Environment :: Console
Classifier: Natural Language :: English
Classifier: Operating System :: OS Independent
Classifier: Programming Language :: Python :: 3
Classifier: Programming Language :: Python :: 3 :: Only
Classifier: Programming Language :: Python :: 3.10
Classifier: Programming Language :: Python :: 3.8
Classifier: Programming Language :: Python :: 3.9
Classifier: Topic :: Office/Business
Classifier: Topic :: Text Editors :: Text Processing
Classifier: Topic :: Utilities
Requires-Dist: beautifulsoup4 (>=4.11.1,<5.0.0)
Requires-Dist: lxml (>=4.9.0,<5.0.0)
Requires-Dist: typer (>=0.4.1,<0.5.0)
Project-URL: Repository, https://github.com/dotcs/ms-word-ieee-patch
